{
	"_settings": {
		"max_total_weight_per_level": [100, 110, 120],
		"default_max_total_weight": 30
	},

	"bat": {
		"entityCategory": "enemy",
		"skills": ["Screech", "Swoop", "Rabies"],
		"sprite_type": "bat",
		"behaviour": ["passive", "enemy_flying"],
		"spawnrate": { "min": 0.0, "max": 0.44642857 },
		"spawncount": { "min": 4, "max": 20 },
		"weight": 3
	},

	"skeleton": {
		"entityCategory": "enemy",
		"skills": ["Eye-Flash-Slash", "Swoop", "Feint"],
		"sprite_type": "skeleton",
		"behaviour": ["hostile", "enemy_walking"],
		"spawnrate": { "min": 0.0, "max": 0.17857143 },
		"spawncount": { "min": 4, "max": 20 },
		"weight": 3
	},

	"base_zombie": {
		"entityCategory": "enemy",
		"skills": ["Screech", "Rabies"],
		"sprite_type": "base_zombie",
		"behaviour": ["hostile", "enemy_walking", "burrowing"],
		"spawnrate": { "min": 0.0, "max": 0.16785714 },
		"spawncount": { "min": 4, "max": 20 },
		"weight": 4
	},

	"ghost": {
		"entityCategory": "enemy",
		"skills": ["Feint", "Encroaching Void"], 
		"sprite_type": "ghost",
		"behaviour": ["hostile", "enemy_flying", "burrowing"],
		"spawnrate": { "min": 0.0, "max": 0.01785714 },
		"spawncount": { "min": 4, "max": 20 },
		"weight": 5
	},

	"what": {
		"entityCategory": "enemy",
		"skills" : ["Screech", "Vortex", "Encroaching Void"],
		"sprite_type": "what",
		"behaviour": ["hostile", "wallbound"],
		"spawnrate": { "min": 0.0, "max": 0.1 },
		"spawncount": { "min": 4, "max": 6 },
		"weight": 6
	},
	
	"orc": {
		"entityCategory": "boss",
		"skills" : ["Big Bonk", "War Command", "Ground Stomp"],
		"sprite_type": "orc",
		"behaviour": ["boss"],
		"spawnrate": { "min": 1, "max": 1 },
		"spawncount": { "min": 1, "max": 1 },
		"weight": 0
	},
	
	"plant": {
		"entityCategory": "boss",
		"skills" : ["Vine Slash", "Entwine", "Poision Ivy", "Herbicide", "Mandrake's Screech"],
		"sprite_type": "plant",
		"behaviour": ["boss"],
		"spawnrate": { "min": 1, "max": 1 },
		"spawncount": { "min": 1, "max": 1 },
		"weight": 0
	},
	
	"wendigo": {
		"entityCategory": "boss",
		"skills" : ["Claw Slash", "Mimicry", "Evil that devours", "Insatiable Hunger"],
		"sprite_type": "wendigo",
		"behaviour": ["boss"],
		"spawnrate": { "min": 1, "max": 1 },
		"spawncount": { "min": 1, "max": 1 },
		"weight": 0
	},
	
	"necromancer": {
		"entityCategory": "boss",
		"skills" : ["Green Flames", "Join the dead", "Domain Expansion", "Life Steal"],
		"sprite_type": "necromancer",
		"behaviour": ["boss"],
		"spawnrate": { "min": 1, "max": 1 },
		"spawncount": { "min": 1, "max": 1 },
		"weight": 0
	},
	
}
